README.md
setup.py
examples/__init__.py
examples/example_application.py
examples/example_application_2.py
tb_rest_client32/__init__.py
tb_rest_client32/api_client.py
tb_rest_client32/configuration.py
tb_rest_client32/rest.py
tb_rest_client32/rest_client_base.py
tb_rest_client32/rest_client_ce.py
tb_rest_client32/rest_client_pe.py
tb_rest_client32.egg-info/PKG-INFO
tb_rest_client32.egg-info/SOURCES.txt
tb_rest_client32.egg-info/dependency_links.txt
tb_rest_client32.egg-info/requires.txt
tb_rest_client32.egg-info/top_level.txt
tb_rest_client32/api/__init__.py
tb_rest_client32/api/api_ce/__init__.py
tb_rest_client32/api/api_ce/admin_controller_api.py
tb_rest_client32/api/api_ce/alarm_controller_api.py
tb_rest_client32/api/api_ce/asset_controller_api.py
tb_rest_client32/api/api_ce/audit_log_controller_api.py
tb_rest_client32/api/api_ce/auth_controller_api.py
tb_rest_client32/api/api_ce/component_descriptor_controller_api.py
tb_rest_client32/api/api_ce/customer_controller_api.py
tb_rest_client32/api/api_ce/dashboard_controller_api.py
tb_rest_client32/api/api_ce/device_api_controller_api.py
tb_rest_client32/api/api_ce/device_controller_api.py
tb_rest_client32/api/api_ce/device_profile_controller_api.py
tb_rest_client32/api/api_ce/entity_query_controller_api.py
tb_rest_client32/api/api_ce/entity_relation_controller_api.py
tb_rest_client32/api/api_ce/entity_view_controller_api.py
tb_rest_client32/api/api_ce/event_controller_api.py
tb_rest_client32/api/api_ce/o_auth_2_config_template_controller_api.py
tb_rest_client32/api/api_ce/o_auth_2_controller_api.py
tb_rest_client32/api/api_ce/queue_controller_api.py
tb_rest_client32/api/api_ce/rpc_controller_api.py
tb_rest_client32/api/api_ce/rule_chain_controller_api.py
tb_rest_client32/api/api_ce/telemetry_controller_api.py
tb_rest_client32/api/api_ce/tenant_controller_api.py
tb_rest_client32/api/api_ce/tenant_profile_controller_api.py
tb_rest_client32/api/api_ce/user_controller_api.py
tb_rest_client32/api/api_ce/widget_type_controller_api.py
tb_rest_client32/api/api_ce/widgets_bundle_controller_api.py
tb_rest_client32/api/api_pe/__init__.py
tb_rest_client32/api/api_pe/admin_controller_api.py
