Metadata-Version: 1.2
Name: tb-rest-client32
Version: 1.2
Summary: ThingsBoard REST API client
Home-page: https://thingsboard.io/docs/reference/python-rest-client/
Author-email: info@thingsboard.io
License: Apache Software License (Apache Software License 2.0)
Download-URL: https://github.com/thingsboard/python_tb_rest_client/archive/1.2.tar.gz
Keywords: IoT,ThingsBoard,ThingsBoard REST API client
Platform: UNKNOWN
Requires-Python: >=3.5
